ankiwictionary/__init__.py
ankiwictionary/cli.py
ankiwictionary/main.py
ankiwictionary/parser.py
ankiwictionary/card_styles/card_body_template.html
ankiwiktionary/__init__.py
ankiwiktionary/cli.py
ankiwiktionary/main.py
ankiwiktionary/parser.py
ankiwiktionary/card_styles/card_body_template.html
build/lib/ankiwictionary/__init__.py
build/lib/ankiwictionary/cli.py
build/lib/ankiwictionary/main.py
build/lib/ankiwictionary/parser.py
build/lib/ankiwiktionary/__init__.py
build/lib/ankiwiktionary/cli.py
build/lib/ankiwiktionary/main.py
build/lib/ankiwiktionary/parser.py
build/lib/build/lib/ankiwictionary/__init__.py
build/lib/build/lib/ankiwictionary/cli.py
build/lib/build/lib/ankiwictionary/main.py
build/lib/build/lib/ankiwictionary/parser.py
ankiwiktionary-0.0.1.dist-info/METADATA
ankiwiktionary-0.0.1.dist-info/WHEEL
ankiwiktionary-0.0.1.dist-info/entry_points.txt
ankiwiktionary-0.0.1.dist-info/top_level.txt
ankiwiktionary-0.0.1.dist-info/RECORD
