Metadata-Version: 2.1
Name: ankiwiktionary
Version: 0.0.1
Summary: Anki cards generating from Wiktionary pages
Home-page: UNKNOWN
Author: Damir Chanyshev
Author-email: hairygeek@yandex.com
License: UNKNOWN
Project-URL: Bug Tracker, https://github.com/hairygeek/ankiwiktionary
Project-URL: Documentation, https://github.com/hairygeek/ankiwiktionary
Project-URL: Source Code, https://github.com/hairygeek/ankiwiktionary
Keywords: anki card generation wiktionary russian
Platform: UNKNOWN
Requires-Dist: lxml (>=4.6.2)
Requires-Dist: yarl (>=1.6.3)
Requires-Dist: Jinja2 (>=2.11.2)
Requires-Dist: click (>=7.1.2)
Requires-Dist: colorama (>=0.4.4)
